LICENSE
README.rst
setup.cfg
setup.py
examples/__init__.py
examples/bundle_example.py
examples/complex_example_with_neo4j.py
examples/file_buffer_example.py
examples/horsemeat_example.py
examples/merge_example.py
examples/merge_fail_example.py
examples/simple_example.py
examples/simple_example_influence.py
examples/simple_example_with_neo4j.py
examples/tests/__init__.py
examples/tests/test_examples.py
prov_db_connector.egg-info/PKG-INFO
prov_db_connector.egg-info/SOURCES.txt
prov_db_connector.egg-info/dependency_links.txt
prov_db_connector.egg-info/not-zip-safe
prov_db_connector.egg-info/requires.txt
prov_db_connector.egg-info/top_level.txt
provdbconnector/__init__.py
provdbconnector/prov_db.py
provdbconnector/db_adapters/__init__.py
provdbconnector/db_adapters/baseadapter.py
provdbconnector/db_adapters/in_memory/__init__.py
provdbconnector/db_adapters/in_memory/simple_in_memory.py
provdbconnector/db_adapters/neo4j/__init__.py
provdbconnector/db_adapters/neo4j/cypher_commands.py
provdbconnector/db_adapters/neo4j/neo4jadapter.py
provdbconnector/exceptions/__init__.py
provdbconnector/exceptions/database.py
provdbconnector/exceptions/provapi.py
provdbconnector/exceptions/utils.py
provdbconnector/tests/__init__.py
provdbconnector/tests/examples.py
provdbconnector/tests/test_prov_db.py
provdbconnector/tests/db_adapters/__init__.py
provdbconnector/tests/db_adapters/test_baseadapter.py
provdbconnector/tests/db_adapters/in_memory/__init__.py
provdbconnector/tests/db_adapters/in_memory/test_simple_in_memory.py
provdbconnector/tests/db_adapters/neo4j/__init__.py
provdbconnector/tests/db_adapters/neo4j/test_neo4jadapter.py
provdbconnector/tests/resources/__init__.py
provdbconnector/tests/utils/__init__.py
provdbconnector/tests/utils/test_converter.py
provdbconnector/tests/utils/test_validator.py
provdbconnector/utils/__init__.py
provdbconnector/utils/converter.py
provdbconnector/utils/serializer.py
provdbconnector/utils/validator.py