Metadata-Version: 2.1
Name: prov-db-connector
Version: 0.5.1
Summary: PROV Database Connector
Home-page: https://github.com/DLR-SC/prov-db-connector
Author: DLR, Stefan Bieliauskas, Martin Stoffers
Author-email: opensource@dlr.de, sb@conts.de, martin.stoffers@studserv.uni-leipzig.de
License: Apache License 2.0
Keywords: provenance,graph,model,PROV,PROV-DM,PROV-JSON,JSON,PROV-XML,PROV-N
Platform: UNKNOWN
Classifier: Development Status :: 1 - Planning
Classifier: Topic :: Software Development :: Libraries :: Python Modules
Classifier: License :: OSI Approved :: Apache Software License
Classifier: Programming Language :: Python :: 3.6
Classifier: Programming Language :: Python :: 3.7
Classifier: Programming Language :: Python :: 3.8
Classifier: Programming Language :: Python :: 3.9
Provides-Extra: test
Provides-Extra: dev
Provides-Extra: docs
License-File: LICENSE
